logscope/__init__.py
logscope/cli.py
logscope/core.py
logscope/database.py
logscope/formatter.py
logscope/handlers.py
logscope/report.py
logscope/tracing.py
logscope/utils.py
logscope/static/pico.min.css
logscope-0.1.10.dist-info/METADATA
logscope-0.1.10.dist-info/WHEEL
logscope-0.1.10.dist-info/entry_points.txt
logscope-0.1.10.dist-info/licenses/LICENSE.txt
logscope-0.1.10.dist-info/RECORD
