Metadata-Version: 2.3
Name: logscope
Version: 0.1.10
Summary: Fancy logging with local SQLite storage.
Author-email: "Samuel S. Watson" <samuel.s.watson@gmail.com>
License: MIT
Requires-Python: >=3.9
